README.md
setup.py
pysmz3/__init__.py
pysmz3/exceptions.py
pysmz3/http.py
pysmz3/smz3.py
pysmz3.egg-info/PKG-INFO
pysmz3.egg-info/SOURCES.txt
pysmz3.egg-info/dependency_links.txt
pysmz3.egg-info/requires.txt
pysmz3.egg-info/top_level.txt