Metadata-Version: 2.1
Name: pysmz3
Version: 1.0.1
Summary: A python module for interacting with samus.link, such as generating new smz3 games and retrieving old games.
Home-page: https://github.com/tcprescott/python-pysmz3
Author: Thomas Prescott
Author-email: tcprescott@gmail.com
License: UNKNOWN
Platform: UNKNOWN
Classifier: Programming Language :: Python :: 3
Classifier: Programming Language :: Python :: 3.6
Classifier: Programming Language :: Python :: 3.7
Classifier: License :: OSI Approved :: Apache Software License
Classifier: Development Status :: 5 - Production/Stable
Classifier: Operating System :: OS Independent
